lconfig/__init__.py
lconfig/config.py
lconfig/config_file.py
lconfig/tests/__init__.py
lconfig/tests/test_config.py
lconfig/tests/test_config_file.py
lconfig-0.2.dist-info/LICENSE
lconfig-0.2.dist-info/METADATA
lconfig-0.2.dist-info/WHEEL
lconfig-0.2.dist-info/top_level.txt
lconfig-0.2.dist-info/RECORD
