Metadata-Version: 2.1
Name: lconfig
Version: 0.2
Summary: Helper class to support YAML configuration files
Home-page: https://github.com/lbacik/python-config
Author: Łukasz Bacik
Author-email: mail@luka.sh
License: LGPLv2.1
Platform: UNKNOWN
Classifier: Operating System :: OS Independent
Classifier: Programming Language :: Python
